LICENSE
MANIFEST.in
README.md
setup.cfg
setup.py
versioneer.py
pytroll_monitor/__init__.py
pytroll_monitor/checkmk_logger.py
pytroll_monitor/createTestcase.py
pytroll_monitor/monitor_hook.py
pytroll_monitor/op5_logger.py
pytroll_monitor/pps_posttroll_hook.py
pytroll_monitor/version.py
pytroll_monitor.egg-info/PKG-INFO
pytroll_monitor.egg-info/SOURCES.txt
pytroll_monitor.egg-info/dependency_links.txt
pytroll_monitor.egg-info/not-zip-safe
pytroll_monitor.egg-info/requires.txt
pytroll_monitor.egg-info/top_level.txt